Workbook
Name Actividades: Base!$E$2:$E$36
Name BD_proyecto: #REF!
Name BD_proyecto: #REF!
Name Data: Consultor!$C$12:$AK$31
Name Data: Septiembre!$C$12:$AK$31
Name Recurso: Recursos!$A$2:$A$12
Name BD_proyecto: #REF!
Name Cliente: Base!$C$2:$C$39
Name Mes: Base!$J$1:$J$12
Name BD_proyecto: #REF!
Name BD_proyecto: #REF!
Name Data: Julio!$C$12:$AK$31
Name BD_proyecto: #REF!
Name BD_proyecto: #REF!
Name BD_proyecto: #REF!
Name BD_proyecto: #REF!
Name Data: Agosto!$C$12:$AK$31
Name BD_Recursos: Recursos!$B$2:$F$12
Name Data_Fecha: Base!$J$1:$L$12
Name Data: Febrero!$C$12:$AK$31
Name Data: Abril!$C$12:$AK$31
Name Data: Noviembre!$C$12:$AK$31
Name Data: Junio!$C$12:$AK$31
Name Data: Marzo!$C$12:$AK$32
Name BD_proyecto: #REF!
Name Data: Octubre!$C$12:$AK$31
Name Data: Mayo!$C$12:$AK$31
Name Supervisor: Base!$D$2:$D$7
Name BD_proyecto: #REF!
Name Data: Diciembre!$C$12:$AK$31
Name Data: Enero!$C$12:$AK$31

Sheet Base
A1: N° | B1: Proyecto | C1: Cliente | D1: Supervisor | E1: Actividades | J1: 01 | K1: 46023 | L1: 46053
A2: 1 | B2: Actividades infraestructura | C2: ACAP - RD | D2: Rosalba Sulbarán | E2: Actualizacion Gateway | J2: 02 | K2: 46054 | L2: 46081
A3: 2 | B3: 202-RHCDS: Construir, Mantener y Custodiar los Documentos en Expedientes de Empleados | C3: Alfonso Rivas | E3: Ajuste de proceso en producción | J3: 03 | K3: 46082 | L3: 46112
A4: 3 | B4: Actividades internas | C4: Banco Activo | D4: Merci Fernandez | E4: Análisis de información | J4: 04 | K4: 46113 | L4: 46142
A5: 4 | B5: Ajuste critico al robot cambio de ambiente SAP AWS - Proceso de abono otras forma de pago | C5: Banco Ficensa | E5: Auditoría | J5: 05 | K5: 46143 | L5: 46173
A6: 5 | B6: Altas y Bajas Colectivas | C6: Banco Plaza | E6: Capacitación Facturacion Web | J6: 06 | K6: 46174 | L6: 46203
A7: 6 | B7: Arquitectura Empresarial Banesco | C7: Banco Proamerica | D7: N/A | E7: Daily Servicio Panamericano | J7: 07 | K7: 46204 | L7: 46234
A8: 7 | B8: Automatización de proceso: Notificación de vencimiento de tarjetas a patronos | C8: Banesco | E8: Desarrollo | J8: 08 | K8: 46235 | L8: 46265
A9: 8 | B9: Automatización de Procesos | C9: Banesco Seguros | E9: Diseño de Soluciones | J9: 09 | K9: 46266 | L9: 46295
A10: 9 | B10: Bus de servicio | C10: Cabo Rojo Coop | E10: Documentación | J10: 10 | K10: 46296 | L10: 46326
A11: 10 | B11: Calcular los aportes de primas de la Póliza HCM para aplicación de descuento mensual al colaborador | C11: Claro Ecuador | E11: Entregables diversos | J11: 11 | K11: 46327 | L11: 46356
A12: 11 | B12: Calificación Crediticia | C12: Farmatodo | E12: Entrevistas | J12: 12 | K12: 46357 | L12: 46387
A13: 13 | B13: Capacitacion Java Microservicio | C13: Feriado | E13: Estabilización de proceso en producción
A14: 14 | B14: Cobranza Domiciliada | C14: Ferretotal | E14: Fallas electricas
A15: 15 | B15: COE | C15: Findeter | E15: Feriado Nacional
A16: 16 | B16: Daily banesco RD | C16: Grupasa | E16: Implantación
A17: 17 | B17: Daily Servicio Panamericano | C17: Grupo SIMAN | E17: Incapacidad
A18: 18 | B18: Desarrollo Rocketbot Prueba de concepto | C18: GTA - Guatemala | E18: Instalacion del Ambiente e Induccion
A19: 19 | B19: Discovery Worshop RPA | C19: Locatel | E19: Ajuste de Matriz de Prueba
A20: 20 | B20: Documentacion bank search | C20: Medtronics | E20: Levantamiento de información y capatización
A21: 21 | B21: Emision de Retenciones | C21: N/A | E21: Monitoreo
A22: 22 | B22: Emision de ticket CANTV | C22: PuntoNet | E22: Permiso para diligencias
A23: 23 | B23: Envío masivo de certificado de seguro | C23: PuntoNet - Ecuador | E23: Permiso por Enfermedad
A24: 24 | B24: Extracción de datos | C24: Seguros Atlántida | E24: Pruebas Certificadas
... A36: 36 | B36: Robotización Banesco Seguros | C36: Tech (CANTV) | E36: Vacaciones
A37: 12 | B37: Robotización de Envío de Pantallas Regulatorias de la Red de Agencias | C37: Feltrex
A38: 37 | B38: Robotización Debida Diligencia (Búsqueda) | C38: Tigo
A39: 38 | B39: Sistema de Gestión de calidad | C39: Todoticket
A40: 39 | B40: Sistema Hondutel
A41: 40 | B41: Soaint
A42: 41 | B42: SUDEBAN
A43: 42 | B43: Taller-Blue Prism
A44: 43 | B44: Tribunal RPA

Sheet Recursos
A1: Nombre y Apellido | B1: Cargo | C1: Documento | D1: Gerencia | E1: Correo | F1: Supervidor
D2: Operaciones
D3: Operaciones
D4: Operaciones
D5: Operaciones
D6: Operaciones
D7: Operaciones
D8: Operaciones
D9: Operaciones
D10: Operaciones
D11: Operaciones
D12: Operaciones

Sheet Consultor
B1: CONTROL DE ACTIVIDADES DE CONSULTORÍA | H1: Mes | L1: Año | P1: 13wmqpA-whSNlF58ROWV2OVGTZe15WSD2ofXuk8FfiXE
H2: 01 | L2: =YEAR(P2) -> 2026 | N2: Fecha: | P2: =TODAY() -> 46090
B3: Consultor:
B4: Cargo: | H4: *Período: | K4: =VLOOKUP(H2,Data_Fecha,2,FALSE) -> 46023 | N4: Hasta: | P4: =EOMONTH(K4,0) -> 46053
B5: C.I.#:
B6: Gerencia: | D6: =INDIRECT("Recursos!d"&MATCH($D$3,[1]Recursos!A:A,0)) -> #ERROR!
B7: Supervisor: | D7: =INDIRECT("Recursos!f"&MATCH($D$3,[1]Recursos!A:A,0)) -> #ERROR!
G9: 1 | H9: =+G9+1 -> 2 | I9: =+H9+1 -> 3 | J9: =+I9+1 -> 4 | K9: =+J9+1 -> 5 | L9: =+K9+1 -> 6 | M9: =+L9+1 -> 7 | N9: =+M9+1 -> 8 | O9: =+N9+1 -> 9 | ... AH9: =+AG9+1 -> 28 | AI9: =IF(H2<>"02",+AH9+1,"X") -> 29 | AJ9: =IF(H2<>"02",+AI9+1,"X") -> 30 | AK9: =IF(LOOKUP(H2,#REF!)=31,31,"X") -> #N/A
B10: N° | C10: PROYECTO | D10: CLIENTE | E10: SUPERVISOR | F10: ACTIVIDAD | G10: =MID("LMMJVSDL",WEEKDAY($K$4+G$9-2,1),1) -> J | H10: =MID("LMMJVSDL",WEEKDAY($K$4+H$9-2,1),1) -> V | I10: =MID("LMMJVSDL",WEEKDAY($K$4+I$9-2,1),1) -> S | J10: =MID("LMMJVSDL",WEEKDAY($K$4+J$9-2,1),1) -> D | K10: =MID("LMMJVSDL",WEEKDAY($K$4+K$9-2,1),1) -> L | L10: =MID("LMMJVSDL",WEEKDAY($K$4+L$9-2,1),1) -> M | M10: =MID("LMMJVSDL",WEEKDAY($K$4+M$9-2,1),1) -> M | N10: =MID("LMMJVSDL",WEEKDAY($K$4+N$9-2,1),1) -> J | ... AH10: =MID("LMMJVSDL",WEEKDAY($K$4+AH$9-2,1),1) -> M | AI10: =IF(AI11=29,MID("LMMJVSDL",WEEKDAY($K$4+AI$9-2,1),1),"X") -> J | AJ10: =IF(AJ11=30,MID("LMMJVSDL",WEEKDAY($K$4+AJ$9-2,1),1),"X") -> V | AK10: =IF(AK11=31,MID("LMMJVSDL",WEEKDAY($K$4+AK$9-2,1),1),"X") -> #N/A | AL10: TOTAL HORAS
G11: 44470 | H11: =G11+1 -> 44471 | I11: =H11+1 -> 44472 | J11: =I11+1 -> 44473 | K11: =J11+1 -> 44474 | L11: =K11+1 -> 44475 | M11: =L11+1 -> 44476 | N11: =M11+1 -> 44477 | O11: =N11+1 -> 44478 | ... AH11: =AG11+1 -> 44497 | AI11: =AI9 -> 29 | AJ11: =AJ9 -> 30 | AK11: =AK9 -> #N/A
B12: 1 | AL12: =SUM(G12:AK12) -> 0
B13: =B12+1 -> 2 | AL13: =SUM(G13:AK13) -> 0
B14: =B13+1 -> 3 | AL14: =SUM(G14:AK14) -> 0
B15: =B14+1 -> 4 | AL15: =SUM(G15:AK15) -> 0
B16: =B15+1 -> 5 | AL16: =SUM(G16:AK16) -> 0
B17: =B16+1 -> 6 | AL17: =SUM(G17:AK17) -> 0
B18: =B17+1 -> 7 | AL18: =SUM(G18:AK18) -> 0
B19: =B18+1 -> 8 | AL19: =SUM(G19:AK19) -> 0
B20: =B19+1 -> 9 | AL20: =SUM(G20:AK20) -> 0
B21: =B20+1 -> 10 | AL21: =SUM(G21:AK21) -> 0
B22: =B21+1 -> 11 | AL22: =SUM(G22:AK22) -> 0
B23: =B22+1 -> 12 | AL23: =SUM(G23:AK23) -> 0
B24: =B23+1 -> 13 | AL24: =SUM(G24:AK24) -> 0
... B29: =B28+1 -> 18 | AL29: =SUM(G29:AK29) -> 0
B30: =B29+1 -> 19
B31: =B30+1 -> 20 | AL31: =SUM(G31:AK31) -> 0
C32: =IF(MIN(G32:X32)<8,"EL TOTAL DE HORAS DIARIAS DEBE SER MÍNIMO 8 --->","CORRECTO") -> EL TOTAL DE HORAS DIARIAS DEBE SER MÍNIMO 8 ---> | G32: =SUM(G12:G31) -> 0 | H32: =SUM(H12:H31) -> 0 | I32: =SUM(I12:I31) -> 0 | J32: =SUM(J12:J31) -> 0 | K32: =SUM(K12:K31) -> 0 | L32: =SUM(L12:L31) -> 0 | M32: =SUM(M12:M31) -> 0 | N32: =SUM(N12:N31) -> 0 | ... AL32: =SUM(AL12:AL31) -> 0
F34: Horas Extras (Solo personal autorizado) --- >
F36: TOTAL MES Horas --- > | G36: =IF(G32+G34<=0,"",G32+G34) | H36: =IF(H32+H34<=0,"",H32+H34) | I36: =IF(I32+I34<=0,"",I32+I34) | J36: =IF(J32+J34<=0,"",J32+J34) | K36: =IF(K32+K34<=0,"",K32+K34) | L36: =IF(L32+L34<=0,"",L32+L34) | M36: =IF(M32+M34<=0,"",M32+M34) | N36: =IF(N32+N34<=0,"",N32+N34) | ... AL36: =IF(AL32+AL34<=0,"",AL32+AL34)
B38: Observaciones

Sheet Enero
B1: CONTROL DE ACTIVIDADES DE CONSULTORÍA | H1: Mes | L1: Año | P1: 13wmqpA-whSNlF58ROWV2OVGTZe15WSD2ofXuk8FfiXE
H2: 01 | L2: =YEAR(P2) -> 2026 | N2: Fecha: | P2: =TODAY() -> 46090
B3: Consultor: | D3: Dayana Russoniello
B4: Cargo: | D4: Consultor de Procesos | H4: *Período: | K4: =VLOOKUP(H2,Data_Fecha,2,FALSE) -> 46023 | N4: Hasta: | P4: =EOMONTH(K4,0) -> 46053
B5: C.I.#: | D5: 16332902 | F5: Feriado
B6: Gerencia: | D6: tecnologia | F6: Bancario
B7: Supervisor: | D7: {=INDIRECT("Recursos!f"&MATCH($D$3,Recursos!A:A,0))} -> #N/A
G9: 1 | H9: =+G9+1 -> 2 | I9: =+H9+1 -> 3 | J9: =+I9+1 -> 4 | K9: =+J9+1 -> 5 | L9: =+K9+1 -> 6 | M9: =+L9+1 -> 7 | N9: =+M9+1 -> 8 | O9: =+N9+1 -> 9 | ... AH9: =+AG9+1 -> 28 | AI9: =IF(H2<>"02",+AH9+1,"X") -> 29 | AJ9: =IF(H2<>"02",+AI9+1,"X") -> 30 | AK9: =IF(I2<>"02",+AJ9+1,"X") -> 31
B10: N° | C10: PROYECTO | D10: CLIENTE | E10: SUPERVISOR | F10: ACTIVIDAD | G10: =MID("LMMJVSDL",WEEKDAY($K$4+G$9-2,1),1) -> J | H10: =MID("LMMJVSDL",WEEKDAY($K$4+H$9-2,1),1) -> V | I10: =MID("LMMJVSDL",WEEKDAY($K$4+I$9-2,1),1) -> S | J10: =MID("LMMJVSDL",WEEKDAY($K$4+J$9-2,1),1) -> D | K10: =MID("LMMJVSDL",WEEKDAY($K$4+K$9-2,1),1) -> L | L10: =MID("LMMJVSDL",WEEKDAY($K$4+L$9-2,1),1) -> M | M10: =MID("LMMJVSDL",WEEKDAY($K$4+M$9-2,1),1) -> M | N10: =MID("LMMJVSDL",WEEKDAY($K$4+N$9-2,1),1) -> J | ... AH10: =MID("LMMJVSDL",WEEKDAY($K$4+AH$9-2,1),1) -> M | AI10: =IF(AI11=29,MID("LMMJVSDL",WEEKDAY($K$4+AI$9-2,1),1),"X") -> J | AJ10: =IF(AJ11=30,MID("LMMJVSDL",WEEKDAY($K$4+AJ$9-2,1),1),"X") -> V | AK10: =IF(AK11=31,MID("LMMJVSDL",WEEKDAY($K$4+AK$9-2,1),1),"X") -> S | AL10: TOTAL HORAS
G11: 44470 | H11: =G11+1 -> 44471 | I11: =H11+1 -> 44472 | J11: =I11+1 -> 44473 | K11: =J11+1 -> 44474 | L11: =K11+1 -> 44475 | M11: =L11+1 -> 44476 | N11: =M11+1 -> 44477 | O11: =N11+1 -> 44478 | ... AH11: =AG11+1 -> 44497 | AI11: 29 | AJ11: =AJ9 -> 30 | AK11: =AK9 -> 31
B12: 1 | C12: Autogestión de Clínicas Web Optimización del Proceso de Facturas” Ticket: 17381 | D12: Banesco Seguros | F12: Pruebas Integrales | H12: 2 | K12: 2 | L12: 2 | M12: 2 | N12: 2 | O12: 2 | S12: 2 | T12: 2 | U12: 2 | V12: 2 | Z12: 2 | AA12: 2 | AB12: 2 | AC12: 2 | AF12: 2 | AL12: =SUM(G12:AK12) -> 30
B13: =B12+1 -> 2 | C13: Autogestión de Clínicas Web Optimización del Proceso de Facturas” Ticket: 17381 | D13: Banesco Seguros | F13: Reuniones | H13: 2 | K13: 2 | L13: 2 | M13: 2 | N13: 2 | O13: 2 | S13: 2 | T13: 2 | U13: 2 | V13: 2 | Z13: 2 | AA13: 2 | AB13: 2 | AC13: 2 | AF13: 2 | AL13: =SUM(G13:AK13) -> 30
B14: =B13+1 -> 3 | C14: Autogestión de Clínicas Web Optimización del Proceso de Facturas” Ticket: 17381 | D14: Banesco Seguros | F14: Análisis de información | H14: 2 | K14: 2 | L14: 2 | M14: 2 | AH14: 5 | AI14: 5 | AJ14: 5 | AL14: =SUM(G14:AK14) -> 23
B15: =B14+1 -> 4 | C15: Autogestión de Clínicas Web Optimización del Proceso de Facturas” Ticket: 17381 | D15: Banesco Seguros | F15: Pruebas Integrales | H15: 2 | K15: 2 | L15: 2 | M15: 2 | N15: 4 | AG15: 5 | AL15: =SUM(G15:AK15) -> 17
B16: =B15+1 -> 5 | C16: Autogestión de Clínicas Web Optimización del Proceso de Facturas” Ticket: 17381 | D16: Banesco Seguros | F16: Pruebas Certificadas | H16: 1 | O16: 4 | S16: 4 | T16: 4 | U16: 4 | V16: 4 | Z16: 4 | AA16: 4 | AB16: 4 | AC16: 4 | AF16: 4 | AL16: =SUM(G16:AK16) -> 41
B17: =B16+1 -> 6 | C17: Autogestión de Clínicas Web Optimización del Proceso de Facturas” Ticket: 17381 | D17: Banesco Seguros | F17: Capacitación Facturacion Web | AG17: 3 | AL17: =SUM(G17:AK17) -> 3
B18: =B17+1 -> 7 | F18: Permiso para diligencias | AL18: =SUM(G18:AK18) -> 0
B19: =B18+1 -> 8 | F19: Estabilización de proceso en producción | AH19: 3 | AI19: 3 | AJ19: 3 | AK19: 9 | AL19: =SUM(G19:AK19) -> 18
B20: =B19+1 -> 9 | AL20: =SUM(G20:AK20) -> 0
B21: =B20+1 -> 10 | AL21: =SUM(G21:AK21) -> 0
B22: =B21+1 -> 11 | AL22: =SUM(G22:AK22) -> 0
B23: =B22+1 -> 12 | AL23: =SUM(G23:AK23) -> 0
B24: =B23+1 -> 13 | AL24: =SUM(G24:AK24) -> 0
B25: =B24+1 -> 14 | AL25: =SUM(G25:AK25) -> 0
B26: =B25+1 -> 15 | AL26: =SUM(G26:AK26) -> 0
B27: =B26+1 -> 16 | AL27: =SUM(G27:AK27) -> 0
B28: =B27+1 -> 17 | AL28: =SUM(G28:AK28) -> 0
B29: =B28+1 -> 18 | AL29: =SUM(G29:AK29) -> 0
B30: =B29+1 -> 19
B31: =B30+1 -> 20 | AL31: =SUM(G31:AK31) -> 0
C32: =IF(MIN(G32:X32)<8,"EL TOTAL DE HORAS DIARIAS DEBE SER MÍNIMO 8 --->","CORRECTO") -> EL TOTAL DE HORAS DIARIAS DEBE SER MÍNIMO 8 ---> | G32: =SUM(G12:G31) -> 0 | H32: =SUM(H12:H31) -> 9 | I32: =SUM(I12:I31) -> 0 | J32: =SUM(J12:J31) -> 0 | K32: =SUM(K12:K31) -> 8 | L32: =SUM(L12:L31) -> 8 | M32: =SUM(M12:M31) -> 8 | N32: =SUM(N12:N31) -> 8 | ... AL32: =SUM(AL12:AL31) -> 162
F34: Horas Extras (Solo personal autorizado) --- >
F36: TOTAL MES Horas --- > | G36: =IF(G32+G34<=0,"",G32+G34) | H36: =IF(H32+H34<=0,"",H32+H34) -> 9 | I36: =IF(I32+I34<=0,"",I32+I34) | J36: =IF(J32+J34<=0,"",J32+J34) | K36: =IF(K32+K34<=0,"",K32+K34) -> 8 | L36: =IF(L32+L34<=0,"",L32+L34) -> 8 | M36: =IF(M32+M34<=0,"",M32+M34) -> 8 | N36: =IF(N32+N34<=0,"",N32+N34) -> 8 | ... AF36: =IF(AF32+AF34<=0,"",AF32+AF34) -> 8 | AG36: 8 | AH36: =IF(AH32+AH34<=0,"",AH32+AH34) -> 8 | AI36: =IF(AI32+AI34<=0,"",AI32+AI34) -> 8 | AJ36: =IF(AJ32+AJ34<=0,"",AJ32+AJ34) -> 8 | AK36: =IF(AK32+AK34<=0,"",AK32+AK34) -> 9 | AL36: =IF(AL32+AL34<=0,"",AL32+AL34) -> 162
B38: Observaciones

Sheet Febrero
B1: CONTROL DE ACTIVIDADES DE CONSULTORÍA | H1: Mes | L1: Año | P1: 13wmqpA-whSNlF58ROWV2OVGTZe15WSD2ofXuk8FfiXE
H2: 02 | L2: =YEAR(P2) -> 2026 | N2: Fecha: | P2: =TODAY() -> 46090
B3: Consultor: | D3: Dayana Russoniello
B4: Cargo: | D4: Consultor de Procesos | H4: *Período: | K4: =VLOOKUP(H2,Data_Fecha,2,FALSE) -> 46054 | N4: Hasta: | P4: =EOMONTH(K4,0) -> 46081
B5: C.I.#: | D5: 16332902 | F5: Feriado
B6: Gerencia: | D6: tecnologia | F6: Bancario
B7: Supervisor: | D7: {=INDIRECT("Recursos!f"&MATCH($D$3,Recursos!A:A,0))} -> #N/A
G9: 1 | H9: =+G9+1 -> 2 | I9: =+H9+1 -> 3 | J9: =+I9+1 -> 4 | K9: =+J9+1 -> 5 | L9: =+K9+1 -> 6 | M9: =+L9+1 -> 7 | N9: =+M9+1 -> 8 | O9: =+N9+1 -> 9 | ... AH9: =+AG9+1 -> 28 | AI9: =IF(H2<>"02",+AH9+1,"X") -> X | AJ9: =IF(H2<>"02",+AI9+1,"X") -> X | AK9: =IF(LOOKUP(H2,#REF!)=31,31,"X") -> #N/A
B10: N° | C10: PROYECTO | D10: CLIENTE | E10: SUPERVISOR | F10: ACTIVIDAD | G10: =MID("LMMJVSDL",WEEKDAY($K$4+G$9-2,1),1) -> D | H10: =MID("LMMJVSDL",WEEKDAY($K$4+H$9-2,1),1) -> L | I10: =MID("LMMJVSDL",WEEKDAY($K$4+I$9-2,1),1) -> M | J10: =MID("LMMJVSDL",WEEKDAY($K$4+J$9-2,1),1) -> M | K10: =MID("LMMJVSDL",WEEKDAY($K$4+K$9-2,1),1) -> J | L10: =MID("LMMJVSDL",WEEKDAY($K$4+L$9-2,1),1) -> V | M10: =MID("LMMJVSDL",WEEKDAY($K$4+M$9-2,1),1) -> S | N10: =MID("LMMJVSDL",WEEKDAY($K$4+N$9-2,1),1) -> D | ... AH10: =MID("LMMJVSDL",WEEKDAY($K$4+AH$9-2,1),1) -> S | AI10: d | AJ10: =IF(AJ11=30,MID("LMMJVSDL",WEEKDAY($K$4+AJ$9-2,1),1),"X") -> X | AK10: =IF(AK11=31,MID("LMMJVSDL",WEEKDAY($K$4+AK$9-2,1),1),"X") -> X | AL10: TOTAL HORAS
G11: 44470 | H11: =G11+1 -> 44471 | I11: =H11+1 -> 44472 | J11: =I11+1 -> 44473 | K11: =J11+1 -> 44474 | L11: =K11+1 -> 44475 | M11: =L11+1 -> 44476 | N11: =M11+1 -> 44477 | O11: =N11+1 -> 44478 | ... AH11: =AG11+1 -> 44497 | AI11: 1 | AJ11: 02 | AK11: 03
B12: 1 | C12: Autogestión de Clínicas Web Optimización del Proceso de Facturas” Ticket: 17381 | D12: Banesco Seguros | E12: Eudelis Gomez | F12: Pruebas Integrales Post Produccion | G12: 6 | H12: 4 | I12: 3 | AL12: =SUM(G12:AK12) -> 13
B13: =B12+1 -> 2 | C13: Autogestión de Clínicas Web Optimización del Proceso de Facturas” Ticket: 17382 | D13: Banesco Seguros | E13: Eudelis Gomez | F13: Preparacion de Data | G13: 1 | H13: 2 | I13: 2 | J13: 2 | AL13: =SUM(G13:AK13) -> 7
B14: =B13+1 -> 3 | C14: Autogestión de Clínicas Web Optimización del Proceso de Facturas” Ticket: 17383 | D14: Banesco Seguros | E14: Eudelis Gomez | F14: Documentación | G14: 1 | H14: 1 | I14: 1 | J14: 2 | AL14: =SUM(G14:AK14) -> 5
B15: =B14+1 -> 4 | C15: Autogestión de Clínicas Web Optimización del Proceso de Facturas” Ticket: 17384 | D15: Banesco Seguros | E15: Eudelis Gomez | F15: Análisis de información | H15: 1 | J15: 2 | L15: 2 | AL15: =SUM(G15:AK15) -> 5
B16: =B15+1 -> 5 | C16: Autogestión de Clínicas Web Optimización del Proceso de Facturas” Ticket: 17385 | D16: Banesco Seguros | E16: Eudelis Gomez | F16: Capacitación Facturacion Web | I16: 2 | J16: 2 | L16: 3 | AL16: =SUM(G16:AK16) -> 7
B17: =B16+1 -> 6 | C17: Ajuste de Documentacion Proyecto Autogestión de clinicas Web | D17: Banesco Seguros | E17: Eudelis Gomez | F17: Documentación | L17: 3 | AL17: =SUM(G17:AK17) -> 3
B18: =B17+1 -> 7 | C18: Permiso | D18: Banesco Seguros | E18: Eudelis Gomez | F18: Vacaciones | O18: 0 | P18: - | Q18: - | R18: - | S18: - | X18: - | Y18: - | Z18: - | AL18: =SUM(G18:AK18) -> 0
B19: =B18+1 -> 8 | C19: Ajuste de Matriz DEF_Plan de Pruebas Canal Ventas Oficial-Tipo de Seguro( Plan Contable) | D19: Banesco Seguros | E19: Eudelis Gomez | F19: Vacaciones | AC19: 8 | AD19: 8 | AE19: - | AF19: - | AG19: - | AL19: =SUM(G19:AK19) -> 16
B20: =B19+1 -> 9 | AL20: =SUM(G20:AK20) -> 0
B21: =B20+1 -> 10 | AL21: =SUM(G21:AK21) -> 0
B22: =B21+1 -> 11 | AL22: =SUM(G22:AK22) -> 0
B23: =B22+1 -> 12 | AL23: =SUM(G23:AK23) -> 0
B24: =B23+1 -> 13 | AL24: =SUM(G24:AK24) -> 0
B25: =B24+1 -> 14 | AL25: =SUM(G25:AK25) -> 0
B26: =B25+1 -> 15 | AL26: =SUM(G26:AK26) -> 0
B27: =B26+1 -> 16 | AL27: =SUM(G27:AK27) -> 0
B28: =B27+1 -> 17 | AL28: =SUM(G28:AK28) -> 0
B29: =B28+1 -> 18 | AL29: =SUM(G29:AK29) -> 0
B30: =B29+1 -> 19
B31: =B30+1 -> 20 | AL31: =SUM(G31:AK31) -> 0
C32: =IF(MIN(G32:X32)<8,"EL TOTAL DE HORAS DIARIAS DEBE SER MÍNIMO 8 --->","CORRECTO") -> EL TOTAL DE HORAS DIARIAS DEBE SER MÍNIMO 8 ---> | G32: =SUM(G12:G31) -> 8 | H32: =SUM(H12:H31) -> 8 | I32: =SUM(I12:I31) -> 8 | J32: =SUM(J12:J31) -> 8 | K32: =SUM(K12:K31) -> 0 | L32: =SUM(L12:L31) -> 8 | M32: =SUM(M12:M31) -> 0 | N32: =SUM(N12:N31) -> 0 | ... AL32: =SUM(AL12:AL31) -> 56
F34: Horas Extras (Solo personal autorizado) --- >
F36: TOTAL MES Horas --- > | G36: =IF(G32+G34<=0,"",G32+G34) -> 8 | H36: =IF(H32+H34<=0,"",H32+H34) -> 8 | I36: =IF(I32+I34<=0,"",I32+I34) -> 8 | J36: =IF(J32+J34<=0,"",J32+J34) -> 8 | K36: =IF(K32+K34<=0,"",K32+K34) | L36: =IF(L32+L34<=0,"",L32+L34) -> 8 | M36: =IF(M32+M34<=0,"",M32+M34) | N36: =IF(N32+N34<=0,"",N32+N34) | ... AL36: =IF(AL32+AL34<=0,"",AL32+AL34) -> 56
B38: Observaciones

Sheet Marzo
B1: CONTROL DE ACTIVIDADES DE CONSULTORÍA | H1: Mes | L1: Año | P1: 13wmqpA-whSNlF58ROWV2OVGTZe15WSD2ofXuk8FfiXE
H2: 03 | L2: =YEAR(P2) -> 2026 | N2: Fecha: | P2: =TODAY() -> 46090
B3: Consultor: | D3: Dayana Russoniello
B4: Cargo: | D4: Consultor de Procesos | H4: *Período: | K4: =VLOOKUP(H2,Data_Fecha,2,FALSE) -> 46082 | N4: Hasta: | P4: =EOMONTH(K4,0) -> 46112
B5: C.I.#: | D5: 16332902 | F5: Feriado
B6: Gerencia: | D6: Gerencia de Técnologia | F6: Bancario
B7: Supervisor: | D7: {=INDIRECT("Recursos!f"&MATCH($D$3,Recursos!A:A,0))} -> #N/A
G9: 1 | H9: =+G9+1 -> 2 | I9: =+H9+1 -> 3 | J9: =+I9+1 -> 4 | K9: =+J9+1 -> 5 | L9: =+K9+1 -> 6 | M9: =+L9+1 -> 7 | N9: =+M9+1 -> 8 | O9: =+N9+1 -> 9 | ... AH9: =+AG9+1 -> 28 | AI9: =IF(H2<>"02",+AH9+1,"X") -> 29 | AJ9: =IF(H2<>"02",+AI9+1,"X") -> 30 | AK9: =IF(LOOKUP(H2,#REF!)=31,31,"X") -> #N/A
B10: N° | C10: PROYECTO | D10: CLIENTE | E10: SUPERVISOR | F10: ACTIVIDAD | G10: =MID("LMMJVSDL",WEEKDAY($K$4+G$9-2,1),1) -> D | H10: =MID("LMMJVSDL",WEEKDAY($K$4+H$9-2,1),1) -> L | I10: =MID("LMMJVSDL",WEEKDAY($K$4+I$9-2,1),1) -> M | J10: =MID("LMMJVSDL",WEEKDAY($K$4+J$9-2,1),1) -> M | K10: =MID("LMMJVSDL",WEEKDAY($K$4+K$9-2,1),1) -> J | L10: =MID("LMMJVSDL",WEEKDAY($K$4+L$9-2,1),1) -> V | M10: =MID("LMMJVSDL",WEEKDAY($K$4+M$9-2,1),1) -> S | N10: =MID("LMMJVSDL",WEEKDAY($K$4+N$9-2,1),1) -> D | ... AJ10: =MID("LMMJVSDL",WEEKDAY($K$4+AJ$9-2,1),1) -> L | AK10: =IF(AK11=31,MID("LMMJVSDL",WEEKDAY($K$4+AK$9-2,1),1),"X") -> #N/A | AL10: TOTAL HORAS
G11: 44470 | H11: =G11+1 -> 44471 | I11: =H11+1 -> 44472 | J11: =I11+1 -> 44473 | K11: =J11+1 -> 44474 | L11: =K11+1 -> 44475 | M11: =L11+1 -> 44476 | N11: =M11+1 -> 44477 | O11: =N11+1 -> 44478 | ... AJ11: =AI11+1 -> 44499 | AK11: =AK9 -> #N/A
B12: 1 | C12: Ajuste de Matriz DEF_Plan de Pruebas Canal Ventas Oficial-Tipo de Seguro( Plan Contable) | D12: Banesco Seguros | E12: Eudelis Gomez | F12: Análisis de información | H12: 4 | I12: 4 | J12: 4 | K12: 4 | L12: 4 | AL12: =SUM(G12:AK12) -> 20
C13: Ajuste de Matriz DEF_Plan de Pruebas Canal Ventas Oficial-Tipo de Seguro( Plan Contable) | D13: Banesco Seguros | E13: Eudelis Gomez | F13: Ajuste de Matriz de Prueba | H13: 3 | I13: 4 | J13: 4 | K13: 4 | L13: 4
B14: =B12+1 -> 2 | C14: CDP- Configuración de Productos (AP Escolar, AP Colectivo e Individual, Funerario Colectivo e Individual, Fraude Tarjetas, RC Patronal) | D14: Banesco Seguros | E14: Eudelis Gomez | F14: Documentación | H14: 1 | I14: 0 | J14: 1 | O14: 5 | AL14: =SUM(G14:AK14) -> 7
B15: =B14+1 -> 3 | D15: Banesco Seguros | E15: Eudelis Gomez | F15: Permiso para diligencias | O15: - | AL15: =SUM(G15:AK15) -> 0
B16: =B15+1 -> 4 | AL16: =SUM(G16:AK16) -> 0
B17: =B16+1 -> 5 | AL17: =SUM(G17:AK17) -> 0
B18: =B17+1 -> 6 | AL18: =SUM(G18:AK18) -> 0
B19: =B18+1 -> 7 | AL19: =SUM(G19:AK19) -> 0
B20: =B19+1 -> 8 | AL20: =SUM(G20:AK20) -> 0
B21: =B20+1 -> 9 | AL21: =SUM(G21:AK21) -> 0
B22: =B21+1 -> 10 | AL22: =SUM(G22:AK22) -> 0
B23: =B22+1 -> 11 | AL23: =SUM(G23:AK23) -> 0
B24: =B23+1 -> 12 | AL24: =SUM(G24:AK24) -> 0
B25: =B24+1 -> 13 | AL25: =SUM(G25:AK25) -> 0
B26: =B25+1 -> 14 | AL26: =SUM(G26:AK26) -> 0
B27: =B26+1 -> 15 | AL27: =SUM(G27:AK27) -> 0
... B30: =B29+1 -> 18 | AL30: =SUM(G30:AK30) -> 0
B31: =B30+1 -> 19
B32: =B31+1 -> 20 | AL32: =SUM(G32:AK32) -> 0
C33: =IF(MIN(G33:X33)<8,"EL TOTAL DE HORAS DIARIAS DEBE SER MÍNIMO 8 --->","CORRECTO") -> EL TOTAL DE HORAS DIARIAS DEBE SER MÍNIMO 8 ---> | G33: =SUM(G12:G32) -> 0 | H33: =SUM(H12:H32) -> 8 | I33: =SUM(I12:I32) -> 8 | J33: =SUM(J12:J32) -> 9 | K33: =SUM(K12:K32) -> 8 | L33: =SUM(L12:L32) -> 8 | M33: =SUM(M12:M32) -> 0 | N33: =SUM(N12:N32) -> 0 | ... AL33: =SUM(AL12:AL32) -> 27
F35: Horas Extras (Solo personal autorizado) --- >
F37: TOTAL MES Horas --- > | G37: =IF(G33+G35<=0,"",G33+G35) | H37: =IF(H33+H35<=0,"",H33+H35) -> 8 | I37: =IF(I33+I35<=0,"",I33+I35) -> 8 | J37: =IF(J33+J35<=0,"",J33+J35) -> 9 | K37: =IF(K33+K35<=0,"",K33+K35) -> 8 | L37: =IF(L33+L35<=0,"",L33+L35) -> 8 | M37: =IF(M33+M35<=0,"",M33+M35) | N37: =IF(N33+N35<=0,"",N33+N35) | ... AL37: =IF(AL33+AL35<=0,"",AL33+AL35) -> 27
B39: Observaciones

Sheet Abril
B1: CONTROL DE ACTIVIDADES DE CONSULTORÍA | H1: Mes | L1: Año | P1: 13wmqpA-whSNlF58ROWV2OVGTZe15WSD2ofXuk8FfiXE
H2: 04 | L2: =YEAR(P2) -> 2026 | N2: Fecha: | P2: =TODAY() -> 46090
B3: Consultor:
B4: Cargo: | H4: *Período: | K4: =VLOOKUP(H2,Data_Fecha,2,FALSE) -> 46113 | N4: Hasta: | P4: =EOMONTH(K4,0) -> 46142
B5: C.I.#: | F5: Feriado
B6: Gerencia: | D6: {=IF(ISERROR(INDIRECT("Recursos!d"&MATCH($D$3,Recursos!A:A,0))),"",(INDIRECT("Recursos!d"&MATCH($D$3,Recursos!A:A,0))))} | F6: Bancario
B7: Supervisor: | D7: {=INDIRECT("Recursos!f"&MATCH($D$3,Recursos!A:A,0))} -> #N/A
G9: 1 | H9: =+G9+1 -> 2 | I9: =+H9+1 -> 3 | J9: =+I9+1 -> 4 | K9: =+J9+1 -> 5 | L9: =+K9+1 -> 6 | M9: =+L9+1 -> 7 | N9: =+M9+1 -> 8 | O9: =+N9+1 -> 9 | ... AH9: =+AG9+1 -> 28 | AI9: =IF(H2<>"02",+AH9+1,"X") -> 29 | AJ9: =IF(H2<>"02",+AI9+1,"X") -> 30 | AK9: =IF(LOOKUP(H2,#REF!)=31,31,"X") -> #N/A
B10: N° | C10: PROYECTO | D10: CLIENTE | E10: SUPERVISOR | F10: ACTIVIDAD | G10: =MID("LMMJVSDL",WEEKDAY($K$4+G$9-2,1),1) -> M | H10: =MID("LMMJVSDL",WEEKDAY($K$4+H$9-2,1),1) -> J | I10: =MID("LMMJVSDL",WEEKDAY($K$4+I$9-2,1),1) -> V | J10: =MID("LMMJVSDL",WEEKDAY($K$4+J$9-2,1),1) -> S | K10: =MID("LMMJVSDL",WEEKDAY($K$4+K$9-2,1),1) -> D | L10: =MID("LMMJVSDL",WEEKDAY($K$4+L$9-2,1),1) -> L | M10: =MID("LMMJVSDL",WEEKDAY($K$4+M$9-2,1),1) -> M | N10: =MID("LMMJVSDL",WEEKDAY($K$4+N$9-2,1),1) -> M | ... AH10: =MID("LMMJVSDL",WEEKDAY($K$4+AH$9-2,1),1) -> M | AI10: =IF(AI11=29,MID("LMMJVSDL",WEEKDAY($K$4+AI$9-2,1),1),"X") -> M | AJ10: =IF(AJ11=30,MID("LMMJVSDL",WEEKDAY($K$4+AJ$9-2,1),1),"X") -> J | AK10: =IF(AK11=31,MID("LMMJVSDL",WEEKDAY($K$4+AK$9-2,1),1),"X") -> #N/A | AL10: TOTAL HORAS
G11: 44470 | H11: =G11+1 -> 44471 | I11: =H11+1 -> 44472 | J11: =I11+1 -> 44473 | K11: =J11+1 -> 44474 | L11: =K11+1 -> 44475 | M11: =L11+1 -> 44476 | N11: =M11+1 -> 44477 | O11: =N11+1 -> 44478 | ... AH11: =AG11+1 -> 44497 | AI11: =AI9 -> 29 | AJ11: =AJ9 -> 30 | AK11: =AK9 -> #N/A
B12: 1 | AL12: =SUM(G12:AK12) -> 0
B13: =B12+1 -> 2 | AL13: =SUM(G13:AK13) -> 0
B14: =B13+1 -> 3 | AL14: =SUM(G14:AK14) -> 0
B15: =B14+1 -> 4 | AL15: =SUM(G15:AK15) -> 0
B16: =B15+1 -> 5 | AL16: =SUM(G16:AK16) -> 0
B17: =B16+1 -> 6 | AL17: =SUM(G17:AK17) -> 0
B18: =B17+1 -> 7 | AL18: =SUM(G18:AK18) -> 0
B19: =B18+1 -> 8 | AL19: =SUM(G19:AK19) -> 0
B20: =B19+1 -> 9 | AL20: =SUM(G20:AK20) -> 0
B21: =B20+1 -> 10 | AL21: =SUM(G21:AK21) -> 0
B22: =B21+1 -> 11 | AL22: =SUM(G22:AK22) -> 0
B23: =B22+1 -> 12 | AL23: =SUM(G23:AK23) -> 0
B24: =B23+1 -> 13 | AL24: =SUM(G24:AK24) -> 0
... B29: =B28+1 -> 18 | AL29: =SUM(G29:AK29) -> 0
B30: =B29+1 -> 19
B31: =B30+1 -> 20 | AL31: =SUM(G31:AK31) -> 0
C32: =IF(MIN(G32:X32)<8,"EL TOTAL DE HORAS DIARIAS DEBE SER MÍNIMO 8 --->","CORRECTO") -> EL TOTAL DE HORAS DIARIAS DEBE SER MÍNIMO 8 ---> | G32: =SUM(G12:G31) -> 0 | H32: =SUM(H12:H31) -> 0 | I32: =SUM(I12:I31) -> 0 | J32: =SUM(J12:J31) -> 0 | K32: =SUM(K12:K31) -> 0 | L32: =SUM(L12:L31) -> 0 | M32: =SUM(M12:M31) -> 0 | N32: =SUM(N12:N31) -> 0 | ... AL32: =SUM(AL12:AL31) -> 0
F34: Horas Extras (Solo personal autorizado) --- >
F36: TOTAL MES Horas --- > | G36: =IF(G32+G34<=0,"",G32+G34) | H36: =IF(H32+H34<=0,"",H32+H34) | I36: =IF(I32+I34<=0,"",I32+I34) | J36: =IF(J32+J34<=0,"",J32+J34) | K36: =IF(K32+K34<=0,"",K32+K34) | L36: =IF(L32+L34<=0,"",L32+L34) | M36: =IF(M32+M34<=0,"",M32+M34) | N36: =IF(N32+N34<=0,"",N32+N34) | ... AL36: =IF(AL32+AL34<=0,"",AL32+AL34)
B38: Observaciones

Sheet Mayo
B1: CONTROL DE ACTIVIDADES DE CONSULTORÍA | H1: Mes | L1: Año | P1: 13wmqpA-whSNlF58ROWV2OVGTZe15WSD2ofXuk8FfiXE
H2: 05 | L2: =YEAR(P2) -> 2026 | N2: Fecha: | P2: =TODAY() -> 46090
B3: Consultor:
B4: Cargo: | H4: *Período: | K4: =VLOOKUP(H2,Data_Fecha,2,FALSE) -> 46143 | N4: Hasta: | P4: =EOMONTH(K4,0) -> 46173
B5: C.I.#: | F5: Feriado
B6: Gerencia: | D6: {=IF(ISERROR(INDIRECT("Recursos!d"&MATCH($D$3,Recursos!A:A,0))),"",(INDIRECT("Recursos!d"&MATCH($D$3,Recursos!A:A,0))))} | F6: Bancario
B7: Supervisor: | D7: {=INDIRECT("Recursos!f"&MATCH($D$3,Recursos!A:A,0))} -> #N/A
G9: 1 | H9: =+G9+1 -> 2 | I9: =+H9+1 -> 3 | J9: =+I9+1 -> 4 | K9: =+J9+1 -> 5 | L9: =+K9+1 -> 6 | M9: =+L9+1 -> 7 | N9: =+M9+1 -> 8 | O9: =+N9+1 -> 9 | ... AH9: =+AG9+1 -> 28 | AI9: =IF(H2<>"02",+AH9+1,"X") -> 29 | AJ9: =IF(H2<>"02",+AI9+1,"X") -> 30 | AK9: =IF(LOOKUP(H2,#REF!)=31,31,"X") -> #N/A
B10: N° | C10: PROYECTO | D10: CLIENTE | E10: SUPERVISOR | F10: ACTIVIDAD | G10: =MID("LMMJVSDL",WEEKDAY($K$4+G$9-2,1),1) -> V | H10: =MID("LMMJVSDL",WEEKDAY($K$4+H$9-2,1),1) -> S | I10: =MID("LMMJVSDL",WEEKDAY($K$4+I$9-2,1),1) -> D | J10: =MID("LMMJVSDL",WEEKDAY($K$4+J$9-2,1),1) -> L | K10: =MID("LMMJVSDL",WEEKDAY($K$4+K$9-2,1),1) -> M | L10: =MID("LMMJVSDL",WEEKDAY($K$4+L$9-2,1),1) -> M | M10: =MID("LMMJVSDL",WEEKDAY($K$4+M$9-2,1),1) -> J | N10: =MID("LMMJVSDL",WEEKDAY($K$4+N$9-2,1),1) -> V | ... AH10: =MID("LMMJVSDL",WEEKDAY($K$4+AH$9-2,1),1) -> J | AI10: =IF(AI11=29,MID("LMMJVSDL",WEEKDAY($K$4+AI$9-2,1),1),"X") -> V | AJ10: =IF(AJ11=30,MID("LMMJVSDL",WEEKDAY($K$4+AJ$9-2,1),1),"X") -> S | AK10: =IF(AK11=31,MID("LMMJVSDL",WEEKDAY($K$4+AK$9-2,1),1),"X") -> #N/A | AL10: TOTAL HORAS
G11: 44470 | H11: =G11+1 -> 44471 | I11: =H11+1 -> 44472 | J11: =I11+1 -> 44473 | K11: =J11+1 -> 44474 | L11: =K11+1 -> 44475 | M11: =L11+1 -> 44476 | N11: =M11+1 -> 44477 | O11: =N11+1 -> 44478 | ... AH11: =AG11+1 -> 44497 | AI11: =AI9 -> 29 | AJ11: =AJ9 -> 30 | AK11: =AK9 -> #N/A
B12: 1 | AL12: =SUM(G12:AK12) -> 0
B13: =B12+1 -> 2 | AL13: =SUM(G13:AK13) -> 0
B14: =B13+1 -> 3 | AL14: =SUM(G14:AK14) -> 0
B15: =B14+1 -> 4 | AL15: =SUM(G15:AK15) -> 0
B16: =B15+1 -> 5 | AL16: =SUM(G16:AK16) -> 0
B17: =B16+1 -> 6 | AL17: =SUM(G17:AK17) -> 0
B18: =B17+1 -> 7 | AL18: =SUM(G18:AK18) -> 0
B19: =B18+1 -> 8 | AL19: =SUM(G19:AK19) -> 0
B20: =B19+1 -> 9 | AL20: =SUM(G20:AK20) -> 0
B21: =B20+1 -> 10 | AL21: =SUM(G21:AK21) -> 0
B22: =B21+1 -> 11 | AL22: =SUM(G22:AK22) -> 0
B23: =B22+1 -> 12 | AL23: =SUM(G23:AK23) -> 0
B24: =B23+1 -> 13 | AL24: =SUM(G24:AK24) -> 0
... B29: =B28+1 -> 18 | AL29: =SUM(G29:AK29) -> 0
B30: =B29+1 -> 19
B31: =B30+1 -> 20 | AL31: =SUM(G31:AK31) -> 0
C32: =IF(MIN(G32:X32)<8,"EL TOTAL DE HORAS DIARIAS DEBE SER MÍNIMO 8 --->","CORRECTO") -> EL TOTAL DE HORAS DIARIAS DEBE SER MÍNIMO 8 ---> | G32: =SUM(G12:G31) -> 0 | H32: =SUM(H12:H31) -> 0 | I32: =SUM(I12:I31) -> 0 | J32: =SUM(J12:J31) -> 0 | K32: =SUM(K12:K31) -> 0 | L32: =SUM(L12:L31) -> 0 | M32: =SUM(M12:M31) -> 0 | N32: =SUM(N12:N31) -> 0 | ... AL32: =SUM(AL12:AL31) -> 0
F34: Horas Extras (Solo personal autorizado) --- >
F36: TOTAL MES Horas --- > | G36: =IF(G32+G34<=0,"",G32+G34) | H36: =IF(H32+H34<=0,"",H32+H34) | I36: =IF(I32+I34<=0,"",I32+I34) | J36: =IF(J32+J34<=0,"",J32+J34) | K36: =IF(K32+K34<=0,"",K32+K34) | L36: =IF(L32+L34<=0,"",L32+L34) | M36: =IF(M32+M34<=0,"",M32+M34) | N36: =IF(N32+N34<=0,"",N32+N34) | ... AL36: =IF(AL32+AL34<=0,"",AL32+AL34)
B38: Observaciones

Sheet Junio
B1: CONTROL DE ACTIVIDADES DE CONSULTORÍA | H1: Mes | L1: Año | P1: 13wmqpA-whSNlF58ROWV2OVGTZe15WSD2ofXuk8FfiXE
H2: 06 | L2: =YEAR(P2) -> 2026 | N2: Fecha: | P2: =TODAY() -> 46090
B3: Consultor:
B4: Cargo: | H4: *Período: | K4: =VLOOKUP(H2,Data_Fecha,2,FALSE) -> 46174 | N4: Hasta: | P4: =EOMONTH(K4,0) -> 46203
B5: C.I.#: | F5: Feriado
B6: Gerencia: | D6: {=IF(ISERROR(INDIRECT("Recursos!d"&MATCH($D$3,Recursos!A:A,0))),"",(INDIRECT("Recursos!d"&MATCH($D$3,Recursos!A:A,0))))} | F6: Bancario
B7: Supervisor: | D7: {=INDIRECT("Recursos!f"&MATCH($D$3,Recursos!A:A,0))} -> #N/A
G9: 1 | H9: =+G9+1 -> 2 | I9: =+H9+1 -> 3 | J9: =+I9+1 -> 4 | K9: =+J9+1 -> 5 | L9: =+K9+1 -> 6 | M9: =+L9+1 -> 7 | N9: =+M9+1 -> 8 | O9: =+N9+1 -> 9 | ... AH9: =+AG9+1 -> 28 | AI9: =IF(H2<>"02",+AH9+1,"X") -> 29 | AJ9: =IF(H2<>"02",+AI9+1,"X") -> 30 | AK9: =IF(I2<>"02",+AJ9+1,"X") -> 31
B10: N° | C10: PROYECTO | D10: CLIENTE | E10: SUPERVISOR | F10: ACTIVIDAD | G10: =MID("LMMJVSDL",WEEKDAY($K$4+G$9-2,1),1) -> L | H10: =MID("LMMJVSDL",WEEKDAY($K$4+H$9-2,1),1) -> M | I10: =MID("LMMJVSDL",WEEKDAY($K$4+I$9-2,1),1) -> M | J10: =MID("LMMJVSDL",WEEKDAY($K$4+J$9-2,1),1) -> J | K10: =MID("LMMJVSDL",WEEKDAY($K$4+K$9-2,1),1) -> V | L10: =MID("LMMJVSDL",WEEKDAY($K$4+L$9-2,1),1) -> S | M10: =MID("LMMJVSDL",WEEKDAY($K$4+M$9-2,1),1) -> D | N10: =MID("LMMJVSDL",WEEKDAY($K$4+N$9-2,1),1) -> L | ... AH10: =MID("LMMJVSDL",WEEKDAY($K$4+AH$9-2,1),1) -> D | AI10: =IF(AI11=29,MID("LMMJVSDL",WEEKDAY($K$4+AI$9-2,1),1),"X") -> L | AJ10: =IF(AJ11=30,MID("LMMJVSDL",WEEKDAY($K$4+AJ$9-2,1),1),"X") -> M | AK10: =IF(AK11=31,MID("LMMJVSDL",WEEKDAY($K$4+AK$9-2,1),1),"X") -> M | AL10: TOTAL HORAS
G11: 44470 | H11: =G11+1 -> 44471 | I11: =H11+1 -> 44472 | J11: =I11+1 -> 44473 | K11: =J11+1 -> 44474 | L11: =K11+1 -> 44475 | M11: =L11+1 -> 44476 | N11: =M11+1 -> 44477 | O11: =N11+1 -> 44478 | ... AH11: =AG11+1 -> 44497 | AI11: =AI9 -> 29 | AJ11: =AJ9 -> 30 | AK11: =AK9 -> 31
B12: 1 | AL12: =SUM(G12:AK12) -> 0
B13: =B12+1 -> 2 | AL13: =SUM(G13:AK13) -> 0
B14: =B13+1 -> 3 | AL14: =SUM(G14:AK14) -> 0
B15: =B14+1 -> 4 | AL15: =SUM(G15:AK15) -> 0
B16: =B15+1 -> 5 | AL16: =SUM(G16:AK16) -> 0
B17: =B16+1 -> 6 | AL17: =SUM(G17:AK17) -> 0
B18: =B17+1 -> 7 | AL18: =SUM(G18:AK18) -> 0
B19: =B18+1 -> 8 | AL19: =SUM(G19:AK19) -> 0
B20: =B19+1 -> 9 | AL20: =SUM(G20:AK20) -> 0
B21: =B20+1 -> 10 | AL21: =SUM(G21:AK21) -> 0
B22: =B21+1 -> 11 | AL22: =SUM(G22:AK22) -> 0
B23: =B22+1 -> 12 | AL23: =SUM(G23:AK23) -> 0
B24: =B23+1 -> 13 | AL24: =SUM(G24:AK24) -> 0
... B29: =B28+1 -> 18 | AL29: =SUM(G29:AK29) -> 0
B30: =B29+1 -> 19
B31: =B30+1 -> 20 | AL31: =SUM(G31:AK31) -> 0
C32: =IF(MIN(G32:X32)<8,"EL TOTAL DE HORAS DIARIAS DEBE SER MÍNIMO 8 --->","CORRECTO") -> EL TOTAL DE HORAS DIARIAS DEBE SER MÍNIMO 8 ---> | G32: =SUM(G12:G31) -> 0 | H32: =SUM(H12:H31) -> 0 | I32: =SUM(I12:I31) -> 0 | J32: =SUM(J12:J31) -> 0 | K32: =SUM(K12:K31) -> 0 | L32: =SUM(L12:L31) -> 0 | M32: =SUM(M12:M31) -> 0 | N32: =SUM(N12:N31) -> 0 | ... AL32: =SUM(AL12:AL31) -> 0
F34: Horas Extras (Solo personal autorizado) --- >
F36: TOTAL MES Horas --- > | G36: =IF(G32+G34<=0,"",G32+G34) | H36: =IF(H32+H34<=0,"",H32+H34) | I36: =IF(I32+I34<=0,"",I32+I34) | J36: =IF(J32+J34<=0,"",J32+J34) | K36: =IF(K32+K34<=0,"",K32+K34) | L36: =IF(L32+L34<=0,"",L32+L34) | M36: =IF(M32+M34<=0,"",M32+M34) | N36: =IF(N32+N34<=0,"",N32+N34) | ... AL36: =IF(AL32+AL34<=0,"",AL32+AL34)
B38: Observaciones

Sheet Julio
B1: CONTROL DE ACTIVIDADES DE CONSULTORÍA | H1: Mes | L1: Año | P1: 13wmqpA-whSNlF58ROWV2OVGTZe15WSD2ofXuk8FfiXE
H2: 07 | L2: =YEAR(P2) -> 2026 | N2: Fecha: | P2: =TODAY() -> 46090
B3: Consultor:
B4: Cargo: | H4: *Período: | K4: =VLOOKUP(H2,Data_Fecha,2,FALSE) -> 46204 | N4: Hasta: | P4: =EOMONTH(K4,0) -> 46234
B5: C.I.#: | F5: Feriado
B6: Gerencia: | D6: {=IF(ISERROR(INDIRECT("Recursos!d"&MATCH($D$3,Recursos!A:A,0))),"",(INDIRECT("Recursos!d"&MATCH($D$3,Recursos!A:A,0))))} | F6: Bancario
B7: Supervisor: | D7: {=INDIRECT("Recursos!f"&MATCH($D$3,Recursos!A:A,0))} -> #N/A
G9: 1 | H9: =+G9+1 -> 2 | I9: =+H9+1 -> 3 | J9: =+I9+1 -> 4 | K9: =+J9+1 -> 5 | L9: =+K9+1 -> 6 | M9: =+L9+1 -> 7 | N9: =+M9+1 -> 8 | O9: =+N9+1 -> 9 | ... AH9: =+AG9+1 -> 28 | AI9: =IF(H2<>"02",+AH9+1,"X") -> 29 | AJ9: =IF(H2<>"02",+AI9+1,"X") -> 30 | AK9: =IF(I2<>"02",+AJ9+1,"X") -> 31
B10: N° | C10: PROYECTO | D10: CLIENTE | E10: SUPERVISOR | F10: ACTIVIDAD | G10: =MID("LMMJVSDL",WEEKDAY($K$4+G$9-2,1),1) -> M | H10: =MID("LMMJVSDL",WEEKDAY($K$4+H$9-2,1),1) -> J | I10: =MID("LMMJVSDL",WEEKDAY($K$4+I$9-2,1),1) -> V | J10: =MID("LMMJVSDL",WEEKDAY($K$4+J$9-2,1),1) -> S | K10: =MID("LMMJVSDL",WEEKDAY($K$4+K$9-2,1),1) -> D | L10: =MID("LMMJVSDL",WEEKDAY($K$4+L$9-2,1),1) -> L | M10: =MID("LMMJVSDL",WEEKDAY($K$4+M$9-2,1),1) -> M | N10: =MID("LMMJVSDL",WEEKDAY($K$4+N$9-2,1),1) -> M | ... AH10: =MID("LMMJVSDL",WEEKDAY($K$4+AH$9-2,1),1) -> M | AI10: =IF(AI11=29,MID("LMMJVSDL",WEEKDAY($K$4+AI$9-2,1),1),"X") -> M | AJ10: =IF(AJ11=30,MID("LMMJVSDL",WEEKDAY($K$4+AJ$9-2,1),1),"X") -> J | AK10: =IF(AK11=31,MID("LMMJVSDL",WEEKDAY($K$4+AK$9-2,1),1),"X") -> V | AL10: TOTAL HORAS
G11: 44470 | H11: =G11+1 -> 44471 | I11: =H11+1 -> 44472 | J11: =I11+1 -> 44473 | K11: =J11+1 -> 44474 | L11: =K11+1 -> 44475 | M11: =L11+1 -> 44476 | N11: =M11+1 -> 44477 | O11: =N11+1 -> 44478 | ... AH11: =AG11+1 -> 44497 | AI11: =AI9 -> 29 | AJ11: =AJ9 -> 30 | AK11: =AK9 -> 31
B12: 1 | AL12: =SUM(G12:AK12) -> 0
B13: =B12+1 -> 2 | AL13: =SUM(G13:AK13) -> 0
B14: =B13+1 -> 3 | AL14: =SUM(G14:AK14) -> 0
B15: =B14+1 -> 4 | AL15: =SUM(G15:AK15) -> 0
B16: =B15+1 -> 5 | AL16: =SUM(G16:AK16) -> 0
B17: =B16+1 -> 6 | AL17: =SUM(G17:AK17) -> 0
B18: =B17+1 -> 7 | AL18: =SUM(G18:AK18) -> 0
B19: =B18+1 -> 8 | AL19: =SUM(G19:AK19) -> 0
B20: =B19+1 -> 9 | AL20: =SUM(G20:AK20) -> 0
B21: =B20+1 -> 10 | AL21: =SUM(G21:AK21) -> 0
B22: =B21+1 -> 11 | AL22: =SUM(G22:AK22) -> 0
B23: =B22+1 -> 12 | AL23: =SUM(G23:AK23) -> 0
B24: =B23+1 -> 13 | AL24: =SUM(G24:AK24) -> 0
... B29: =B28+1 -> 18 | AL29: =SUM(G29:AK29) -> 0
B30: =B29+1 -> 19
B31: =B30+1 -> 20 | AL31: =SUM(G31:AK31) -> 0
C32: =IF(MIN(G32:X32)<8,"EL TOTAL DE HORAS DIARIAS DEBE SER MÍNIMO 8 --->","CORRECTO") -> EL TOTAL DE HORAS DIARIAS DEBE SER MÍNIMO 8 ---> | G32: =SUM(G12:G31) -> 0 | H32: =SUM(H12:H31) -> 0 | I32: =SUM(I12:I31) -> 0 | J32: =SUM(J12:J31) -> 0 | K32: =SUM(K12:K31) -> 0 | L32: =SUM(L12:L31) -> 0 | M32: =SUM(M12:M31) -> 0 | N32: =SUM(N12:N31) -> 0 | ... AL32: =SUM(AL12:AL31) -> 0
F34: Horas Extras (Solo personal autorizado) --- >
F36: TOTAL MES Horas --- > | G36: =IF(G32+G34<=0,"",G32+G34) | H36: =IF(H32+H34<=0,"",H32+H34) | I36: =IF(I32+I34<=0,"",I32+I34) | J36: =IF(J32+J34<=0,"",J32+J34) | K36: =IF(K32+K34<=0,"",K32+K34) | L36: =IF(L32+L34<=0,"",L32+L34) | M36: =IF(M32+M34<=0,"",M32+M34) | N36: =IF(N32+N34<=0,"",N32+N34) | ... AL36: =IF(AL32+AL34<=0,"",AL32+AL34)
B38: Observaciones

Sheet Agosto
B1: CONTROL DE ACTIVIDADES DE CONSULTORÍA | H1: Mes | L1: Año | P1: 13wmqpA-whSNlF58ROWV2OVGTZe15WSD2ofXuk8FfiXE
H2: 08 | L2: =YEAR(P2) -> 2026 | N2: Fecha: | P2: =TODAY() -> 46090
B3: Consultor:
B4: Cargo: | H4: *Período: | K4: =VLOOKUP(H2,Data_Fecha,2,FALSE) -> 46235 | N4: Hasta: | P4: =EOMONTH(K4,0) -> 46265
B5: C.I.#: | F5: Feriado
B6: Gerencia: | D6: {=IF(ISERROR(INDIRECT("Recursos!d"&MATCH($D$3,Recursos!A:A,0))),"",(INDIRECT("Recursos!d"&MATCH($D$3,Recursos!A:A,0))))} | F6: Bancario
B7: Supervisor: | D7: {=INDIRECT("Recursos!f"&MATCH($D$3,Recursos!A:A,0))} -> #N/A
G9: 1 | H9: =+G9+1 -> 2 | I9: =+H9+1 -> 3 | J9: =+I9+1 -> 4 | K9: =+J9+1 -> 5 | L9: =+K9+1 -> 6 | M9: =+L9+1 -> 7 | N9: =+M9+1 -> 8 | O9: =+N9+1 -> 9 | ... AH9: =+AG9+1 -> 28 | AI9: =IF(H2<>"02",+AH9+1,"X") -> 29 | AJ9: =IF(H2<>"02",+AI9+1,"X") -> 30 | AK9: =IF(I2<>"02",+AJ9+1,"X") -> 31
B10: N° | C10: PROYECTO | D10: CLIENTE | E10: SUPERVISOR | F10: ACTIVIDAD | G10: =MID("LMMJVSDL",WEEKDAY($K$4+G$9-2,1),1) -> S | H10: =MID("LMMJVSDL",WEEKDAY($K$4+H$9-2,1),1) -> D | I10: =MID("LMMJVSDL",WEEKDAY($K$4+I$9-2,1),1) -> L | J10: =MID("LMMJVSDL",WEEKDAY($K$4+J$9-2,1),1) -> M | K10: =MID("LMMJVSDL",WEEKDAY($K$4+K$9-2,1),1) -> M | L10: =MID("LMMJVSDL",WEEKDAY($K$4+L$9-2,1),1) -> J | M10: =MID("LMMJVSDL",WEEKDAY($K$4+M$9-2,1),1) -> V | N10: =MID("LMMJVSDL",WEEKDAY($K$4+N$9-2,1),1) -> S | ... AH10: =MID("LMMJVSDL",WEEKDAY($K$4+AH$9-2,1),1) -> V | AI10: =IF(AI11=29,MID("LMMJVSDL",WEEKDAY($K$4+AI$9-2,1),1),"X") -> S | AJ10: =IF(AJ11=30,MID("LMMJVSDL",WEEKDAY($K$4+AJ$9-2,1),1),"X") -> D | AK10: =IF(AK11=31,MID("LMMJVSDL",WEEKDAY($K$4+AK$9-2,1),1),"X") -> L | AL10: TOTAL HORAS
G11: 44470 | H11: =G11+1 -> 44471 | I11: =H11+1 -> 44472 | J11: =I11+1 -> 44473 | K11: =J11+1 -> 44474 | L11: =K11+1 -> 44475 | M11: =L11+1 -> 44476 | N11: =M11+1 -> 44477 | O11: =N11+1 -> 44478 | ... AH11: =AG11+1 -> 44497 | AI11: =AI9 -> 29 | AJ11: =AJ9 -> 30 | AK11: =AK9 -> 31
B12: 1 | AL12: =SUM(G12:AK12) -> 0
B13: =B12+1 -> 2 | AL13: =SUM(G13:AK13) -> 0
B14: =B13+1 -> 3 | AL14: =SUM(G14:AK14) -> 0
B15: =B14+1 -> 4 | AL15: =SUM(G15:AK15) -> 0
B16: =B15+1 -> 5 | AL16: =SUM(G16:AK16) -> 0
B17: =B16+1 -> 6 | AL17: =SUM(G17:AK17) -> 0
B18: =B17+1 -> 7 | AL18: =SUM(G18:AK18) -> 0
B19: =B18+1 -> 8 | AL19: =SUM(G19:AK19) -> 0
B20: =B19+1 -> 9 | AL20: =SUM(G20:AK20) -> 0
B21: =B20+1 -> 10 | AL21: =SUM(G21:AK21) -> 0
B22: =B21+1 -> 11 | AL22: =SUM(G22:AK22) -> 0
B23: =B22+1 -> 12 | AL23: =SUM(G23:AK23) -> 0
B24: =B23+1 -> 13 | AL24: =SUM(G24:AK24) -> 0
... B29: =B28+1 -> 18 | AL29: =SUM(G29:AK29) -> 0
B30: =B29+1 -> 19
B31: =B30+1 -> 20 | AL31: =SUM(G31:AK31) -> 0
C32: =IF(MIN(G32:X32)<8,"EL TOTAL DE HORAS DIARIAS DEBE SER MÍNIMO 8 --->","CORRECTO") -> EL TOTAL DE HORAS DIARIAS DEBE SER MÍNIMO 8 ---> | G32: =SUM(G12:G31) -> 0 | H32: =SUM(H12:H31) -> 0 | I32: =SUM(I12:I31) -> 0 | J32: =SUM(J12:J31) -> 0 | K32: =SUM(K12:K31) -> 0 | L32: =SUM(L12:L31) -> 0 | M32: =SUM(M12:M31) -> 0 | N32: =SUM(N12:N31) -> 0 | ... AL32: =SUM(AL12:AL31) -> 0
F34: Horas Extras (Solo personal autorizado) --- >
F36: TOTAL MES Horas --- > | G36: =IF(G32+G34<=0,"",G32+G34) | H36: =IF(H32+H34<=0,"",H32+H34) | I36: =IF(I32+I34<=0,"",I32+I34) | J36: =IF(J32+J34<=0,"",J32+J34) | K36: =IF(K32+K34<=0,"",K32+K34) | L36: =IF(L32+L34<=0,"",L32+L34) | M36: =IF(M32+M34<=0,"",M32+M34) | N36: =IF(N32+N34<=0,"",N32+N34) | ... AL36: =IF(AL32+AL34<=0,"",AL32+AL34)
B38: Observaciones

Sheet Septiembre
B1: CONTROL DE ACTIVIDADES DE CONSULTORÍA | H1: Mes | L1: Año | P1: 13wmqpA-whSNlF58ROWV2OVGTZe15WSD2ofXuk8FfiXE
H2: 09 | L2: =YEAR(P2) -> 2026 | N2: Fecha: | P2: =TODAY() -> 46090
B3: Consultor:
B4: Cargo: | H4: *Período: | K4: =VLOOKUP(H2,Data_Fecha,2,FALSE) -> 46266 | N4: Hasta: | P4: =EOMONTH(K4,0) -> 46295
B5: C.I.#: | F5: Feriado
B6: Gerencia: | D6: {=IF(ISERROR(INDIRECT("Recursos!d"&MATCH($D$3,Recursos!A:A,0))),"",(INDIRECT("Recursos!d"&MATCH($D$3,Recursos!A:A,0))))} | F6: Bancario
B7: Supervisor: | D7: {=INDIRECT("Recursos!f"&MATCH($D$3,Recursos!A:A,0))} -> #N/A
G9: 1 | H9: =+G9+1 -> 2 | I9: =+H9+1 -> 3 | J9: =+I9+1 -> 4 | K9: =+J9+1 -> 5 | L9: =+K9+1 -> 6 | M9: =+L9+1 -> 7 | N9: =+M9+1 -> 8 | O9: =+N9+1 -> 9 | ... AH9: =+AG9+1 -> 28 | AI9: =IF(H2<>"02",+AH9+1,"X") -> 29 | AJ9: =IF(H2<>"02",+AI9+1,"X") -> 30 | AK9: =IF(I2<>"02",+AJ9+1,"X") -> 31
B10: N° | C10: PROYECTO | D10: CLIENTE | E10: SUPERVISOR | F10: ACTIVIDAD | G10: =MID("LMMJVSDL",WEEKDAY($K$4+G$9-2,1),1) -> M | H10: =MID("LMMJVSDL",WEEKDAY($K$4+H$9-2,1),1) -> M | I10: =MID("LMMJVSDL",WEEKDAY($K$4+I$9-2,1),1) -> J | J10: =MID("LMMJVSDL",WEEKDAY($K$4+J$9-2,1),1) -> V | K10: =MID("LMMJVSDL",WEEKDAY($K$4+K$9-2,1),1) -> S | L10: =MID("LMMJVSDL",WEEKDAY($K$4+L$9-2,1),1) -> D | M10: =MID("LMMJVSDL",WEEKDAY($K$4+M$9-2,1),1) -> L | N10: =MID("LMMJVSDL",WEEKDAY($K$4+N$9-2,1),1) -> M | ... AH10: =MID("LMMJVSDL",WEEKDAY($K$4+AH$9-2,1),1) -> L | AI10: =IF(AI11=29,MID("LMMJVSDL",WEEKDAY($K$4+AI$9-2,1),1),"X") -> M | AJ10: =IF(AJ11=30,MID("LMMJVSDL",WEEKDAY($K$4+AJ$9-2,1),1),"X") -> M | AK10: =IF(AK11=31,MID("LMMJVSDL",WEEKDAY($K$4+AK$9-2,1),1),"X") -> J | AL10: TOTAL HORAS
G11: 44470 | H11: =G11+1 -> 44471 | I11: =H11+1 -> 44472 | J11: =I11+1 -> 44473 | K11: =J11+1 -> 44474 | L11: =K11+1 -> 44475 | M11: =L11+1 -> 44476 | N11: =M11+1 -> 44477 | O11: =N11+1 -> 44478 | ... AH11: =AG11+1 -> 44497 | AI11: =AI9 -> 29 | AJ11: =AJ9 -> 30 | AK11: =AK9 -> 31
B12: 1 | AL12: =SUM(G12:AK12) -> 0
B13: =B12+1 -> 2 | AL13: =SUM(G13:AK13) -> 0
B14: =B13+1 -> 3 | AL14: =SUM(G14:AK14) -> 0
B15: =B14+1 -> 4 | AL15: =SUM(G15:AK15) -> 0
B16: =B15+1 -> 5 | AL16: =SUM(G16:AK16) -> 0
B17: =B16+1 -> 6 | AL17: =SUM(G17:AK17) -> 0
B18: =B17+1 -> 7 | AL18: =SUM(G18:AK18) -> 0
B19: =B18+1 -> 8 | AL19: =SUM(G19:AK19) -> 0
B20: =B19+1 -> 9 | AL20: =SUM(G20:AK20) -> 0
B21: =B20+1 -> 10 | AL21: =SUM(G21:AK21) -> 0
B22: =B21+1 -> 11 | AL22: =SUM(G22:AK22) -> 0
B23: =B22+1 -> 12 | AL23: =SUM(G23:AK23) -> 0
B24: =B23+1 -> 13 | AL24: =SUM(G24:AK24) -> 0
... B29: =B28+1 -> 18 | AL29: =SUM(G29:AK29) -> 0
B30: =B29+1 -> 19
B31: =B30+1 -> 20 | AL31: =SUM(G31:AK31) -> 0
C32: =IF(MIN(G32:X32)<8,"EL TOTAL DE HORAS DIARIAS DEBE SER MÍNIMO 8 --->","CORRECTO") -> EL TOTAL DE HORAS DIARIAS DEBE SER MÍNIMO 8 ---> | G32: =SUM(G12:G31) -> 0 | H32: =SUM(H12:H31) -> 0 | I32: =SUM(I12:I31) -> 0 | J32: =SUM(J12:J31) -> 0 | K32: =SUM(K12:K31) -> 0 | L32: =SUM(L12:L31) -> 0 | M32: =SUM(M12:M31) -> 0 | N32: =SUM(N12:N31) -> 0 | ... AL32: =SUM(AL12:AL31) -> 0
F34: Horas Extras (Solo personal autorizado) --- >
F36: TOTAL MES Horas --- > | G36: =IF(G32+G34<=0,"",G32+G34) | H36: =IF(H32+H34<=0,"",H32+H34) | I36: =IF(I32+I34<=0,"",I32+I34) | J36: =IF(J32+J34<=0,"",J32+J34) | K36: =IF(K32+K34<=0,"",K32+K34) | L36: =IF(L32+L34<=0,"",L32+L34) | M36: =IF(M32+M34<=0,"",M32+M34) | N36: =IF(N32+N34<=0,"",N32+N34) | ... AL36: =IF(AL32+AL34<=0,"",AL32+AL34)
B38: Observaciones

Sheet Octubre
B1: CONTROL DE ACTIVIDADES DE CONSULTORÍA | H1: Mes | L1: Año | P1: 13wmqpA-whSNlF58ROWV2OVGTZe15WSD2ofXuk8FfiXE
H2: 10 | L2: =YEAR(P2) -> 2026 | N2: Fecha: | P2: =TODAY() -> 46090
B3: Consultor:
B4: Cargo: | H4: *Período: | K4: =VLOOKUP(H2,Data_Fecha,2,FALSE) -> 46296 | N4: Hasta: | P4: =EOMONTH(K4,0) -> 46326
B5: C.I.#: | F5: Feriado
B6: Gerencia: | D6: {=IF(ISERROR(INDIRECT("Recursos!d"&MATCH($D$3,Recursos!A:A,0))),"",(INDIRECT("Recursos!d"&MATCH($D$3,Recursos!A:A,0))))} | F6: Bancario
B7: Supervisor: | D7: {=INDIRECT("Recursos!f"&MATCH($D$3,Recursos!A:A,0))} -> #N/A
G9: 1 | H9: =+G9+1 -> 2 | I9: =+H9+1 -> 3 | J9: =+I9+1 -> 4 | K9: =+J9+1 -> 5 | L9: =+K9+1 -> 6 | M9: =+L9+1 -> 7 | N9: =+M9+1 -> 8 | O9: =+N9+1 -> 9 | ... AH9: =+AG9+1 -> 28 | AI9: =IF(H2<>"02",+AH9+1,"X") -> 29 | AJ9: =IF(H2<>"02",+AI9+1,"X") -> 30 | AK9: =IF(I2<>"02",+AJ9+1,"X") -> 31
B10: N° | C10: PROYECTO | D10: CLIENTE | E10: SUPERVISOR | F10: ACTIVIDAD | G10: =MID("LMMJVSDL",WEEKDAY($K$4+G$9-2,1),1) -> J | H10: =MID("LMMJVSDL",WEEKDAY($K$4+H$9-2,1),1) -> V | I10: =MID("LMMJVSDL",WEEKDAY($K$4+I$9-2,1),1) -> S | J10: =MID("LMMJVSDL",WEEKDAY($K$4+J$9-2,1),1) -> D | K10: =MID("LMMJVSDL",WEEKDAY($K$4+K$9-2,1),1) -> L | L10: =MID("LMMJVSDL",WEEKDAY($K$4+L$9-2,1),1) -> M | M10: =MID("LMMJVSDL",WEEKDAY($K$4+M$9-2,1),1) -> M | N10: =MID("LMMJVSDL",WEEKDAY($K$4+N$9-2,1),1) -> J | ... AH10: =MID("LMMJVSDL",WEEKDAY($K$4+AH$9-2,1),1) -> M | AI10: =IF(AI11=29,MID("LMMJVSDL",WEEKDAY($K$4+AI$9-2,1),1),"X") -> J | AJ10: =IF(AJ11=30,MID("LMMJVSDL",WEEKDAY($K$4+AJ$9-2,1),1),"X") -> V | AK10: =IF(AK11=31,MID("LMMJVSDL",WEEKDAY($K$4+AK$9-2,1),1),"X") -> S | AL10: TOTAL HORAS
G11: 44470 | H11: =G11+1 -> 44471 | I11: =H11+1 -> 44472 | J11: =I11+1 -> 44473 | K11: =J11+1 -> 44474 | L11: =K11+1 -> 44475 | M11: =L11+1 -> 44476 | N11: =M11+1 -> 44477 | O11: =N11+1 -> 44478 | ... AH11: =AG11+1 -> 44497 | AI11: =AI9 -> 29 | AJ11: =AJ9 -> 30 | AK11: =AK9 -> 31
B12: 1 | AL12: =SUM(G12:AK12) -> 0
B13: =B12+1 -> 2 | AL13: =SUM(G13:AK13) -> 0
B14: =B13+1 -> 3 | AL14: =SUM(G14:AK14) -> 0
B15: =B14+1 -> 4 | AL15: =SUM(G15:AK15) -> 0
B16: =B15+1 -> 5 | AL16: =SUM(G16:AK16) -> 0
B17: =B16+1 -> 6 | AL17: =SUM(G17:AK17) -> 0
B18: =B17+1 -> 7 | AL18: =SUM(G18:AK18) -> 0
B19: =B18+1 -> 8 | AL19: =SUM(G19:AK19) -> 0
B20: =B19+1 -> 9 | AL20: =SUM(G20:AK20) -> 0
B21: =B20+1 -> 10 | AL21: =SUM(G21:AK21) -> 0
B22: =B21+1 -> 11 | AL22: =SUM(G22:AK22) -> 0
B23: =B22+1 -> 12 | AL23: =SUM(G23:AK23) -> 0
B24: =B23+1 -> 13 | AL24: =SUM(G24:AK24) -> 0
... B29: =B28+1 -> 18 | AL29: =SUM(G29:AK29) -> 0
B30: =B29+1 -> 19
B31: =B30+1 -> 20 | AL31: =SUM(G31:AK31) -> 0
C32: =IF(MIN(G32:X32)<8,"EL TOTAL DE HORAS DIARIAS DEBE SER MÍNIMO 8 --->","CORRECTO") -> EL TOTAL DE HORAS DIARIAS DEBE SER MÍNIMO 8 ---> | G32: =SUM(G12:G31) -> 0 | H32: =SUM(H12:H31) -> 0 | I32: =SUM(I12:I31) -> 0 | J32: =SUM(J12:J31) -> 0 | K32: =SUM(K12:K31) -> 0 | L32: =SUM(L12:L31) -> 0 | M32: =SUM(M12:M31) -> 0 | N32: =SUM(N12:N31) -> 0 | ... AL32: =SUM(AL12:AL31) -> 0
F34: Horas Extras (Solo personal autorizado) --- >
F36: TOTAL MES Horas --- > | G36: =IF(G32+G34<=0,"",G32+G34) | H36: =IF(H32+H34<=0,"",H32+H34) | I36: =IF(I32+I34<=0,"",I32+I34) | J36: =IF(J32+J34<=0,"",J32+J34) | K36: =IF(K32+K34<=0,"",K32+K34) | L36: =IF(L32+L34<=0,"",L32+L34) | M36: =IF(M32+M34<=0,"",M32+M34) | N36: =IF(N32+N34<=0,"",N32+N34) | ... AL36: =IF(AL32+AL34<=0,"",AL32+AL34)
B38: Observaciones

Sheet Noviembre
B1: CONTROL DE ACTIVIDADES DE CONSULTORÍA | H1: Mes | L1: Año | P1: 13wmqpA-whSNlF58ROWV2OVGTZe15WSD2ofXuk8FfiXE
H2: 11 | L2: =YEAR(P2) -> 2026 | N2: Fecha: | P2: =TODAY() -> 46090
B3: Consultor:
B4: Cargo: | H4: *Período: | K4: =VLOOKUP(H2,Data_Fecha,2,FALSE) -> 46327 | N4: Hasta: | P4: =EOMONTH(K4,0) -> 46356
B5: C.I.#: | F5: Feriado
B6: Gerencia: | D6: {=IF(ISERROR(INDIRECT("Recursos!d"&MATCH($D$3,Recursos!A:A,0))),"",(INDIRECT("Recursos!d"&MATCH($D$3,Recursos!A:A,0))))} | F6: Bancario
B7: Supervisor: | D7: {=INDIRECT("Recursos!f"&MATCH($D$3,Recursos!A:A,0))} -> #N/A
G9: 1 | H9: =+G9+1 -> 2 | I9: =+H9+1 -> 3 | J9: =+I9+1 -> 4 | K9: =+J9+1 -> 5 | L9: =+K9+1 -> 6 | M9: =+L9+1 -> 7 | N9: =+M9+1 -> 8 | O9: =+N9+1 -> 9 | ... AH9: =+AG9+1 -> 28 | AI9: =IF(H2<>"02",+AH9+1,"X") -> 29 | AJ9: =IF(H2<>"02",+AI9+1,"X") -> 30 | AK9: =IF(LOOKUP(H2,#REF!)=31,31,"X") -> #N/A
B10: N° | C10: PROYECTO | D10: CLIENTE | E10: SUPERVISOR | F10: ACTIVIDAD | G10: =MID("LMMJVSDL",WEEKDAY($K$4+G$9-2,1),1) -> D | H10: =MID("LMMJVSDL",WEEKDAY($K$4+H$9-2,1),1) -> L | I10: =MID("LMMJVSDL",WEEKDAY($K$4+I$9-2,1),1) -> M | J10: =MID("LMMJVSDL",WEEKDAY($K$4+J$9-2,1),1) -> M | K10: =MID("LMMJVSDL",WEEKDAY($K$4+K$9-2,1),1) -> J | L10: =MID("LMMJVSDL",WEEKDAY($K$4+L$9-2,1),1) -> V | M10: =MID("LMMJVSDL",WEEKDAY($K$4+M$9-2,1),1) -> S | N10: =MID("LMMJVSDL",WEEKDAY($K$4+N$9-2,1),1) -> D | ... AH10: =MID("LMMJVSDL",WEEKDAY($K$4+AH$9-2,1),1) -> S | AI10: =IF(AI11=29,MID("LMMJVSDL",WEEKDAY($K$4+AI$9-2,1),1),"X") -> D | AJ10: =IF(AJ11=30,MID("LMMJVSDL",WEEKDAY($K$4+AJ$9-2,1),1),"X") -> L | AK10: =IF(AK11=31,MID("LMMJVSDL",WEEKDAY($K$4+AK$9-2,1),1),"X") -> #N/A | AL10: TOTAL HORAS
G11: 44470 | H11: =G11+1 -> 44471 | I11: =H11+1 -> 44472 | J11: =I11+1 -> 44473 | K11: =J11+1 -> 44474 | L11: =K11+1 -> 44475 | M11: =L11+1 -> 44476 | N11: =M11+1 -> 44477 | O11: =N11+1 -> 44478 | ... AH11: =AG11+1 -> 44497 | AI11: =AI9 -> 29 | AJ11: =AJ9 -> 30 | AK11: =AK9 -> #N/A
B12: 1 | AL12: =SUM(G12:AK12) -> 0
B13: =B12+1 -> 2 | AL13: =SUM(G13:AK13) -> 0
B14: =B13+1 -> 3 | AL14: =SUM(G14:AK14) -> 0
B15: =B14+1 -> 4 | AL15: =SUM(G15:AK15) -> 0
B16: =B15+1 -> 5 | AL16: =SUM(G16:AK16) -> 0
B17: =B16+1 -> 6 | AL17: =SUM(G17:AK17) -> 0
B18: =B17+1 -> 7 | AL18: =SUM(G18:AK18) -> 0
B19: =B18+1 -> 8 | AL19: =SUM(G19:AK19) -> 0
B20: =B19+1 -> 9 | AL20: =SUM(G20:AK20) -> 0
B21: =B20+1 -> 10 | AL21: =SUM(G21:AK21) -> 0
B22: =B21+1 -> 11 | AL22: =SUM(G22:AK22) -> 0
B23: =B22+1 -> 12 | AL23: =SUM(G23:AK23) -> 0
B24: =B23+1 -> 13 | AL24: =SUM(G24:AK24) -> 0
... B29: =B28+1 -> 18 | AL29: =SUM(G29:AK29) -> 0
B30: =B29+1 -> 19
B31: =B30+1 -> 20 | AL31: =SUM(G31:AK31) -> 0
C32: =IF(MIN(G32:X32)<8,"EL TOTAL DE HORAS DIARIAS DEBE SER MÍNIMO 8 --->","CORRECTO") -> EL TOTAL DE HORAS DIARIAS DEBE SER MÍNIMO 8 ---> | G32: =SUM(G12:G31) -> 0 | H32: =SUM(H12:H31) -> 0 | I32: =SUM(I12:I31) -> 0 | J32: =SUM(J12:J31) -> 0 | K32: =SUM(K12:K31) -> 0 | L32: =SUM(L12:L31) -> 0 | M32: =SUM(M12:M31) -> 0 | N32: =SUM(N12:N31) -> 0 | ... AL32: =SUM(AL12:AL31) -> 0
F34: Horas Extras (Solo personal autorizado) --- >
F36: TOTAL MES Horas --- > | G36: =IF(G32+G34<=0,"",G32+G34) | H36: =IF(H32+H34<=0,"",H32+H34) | I36: =IF(I32+I34<=0,"",I32+I34) | J36: =IF(J32+J34<=0,"",J32+J34) | K36: =IF(K32+K34<=0,"",K32+K34) | L36: =IF(L32+L34<=0,"",L32+L34) | M36: =IF(M32+M34<=0,"",M32+M34) | N36: =IF(N32+N34<=0,"",N32+N34) | ... AL36: =IF(AL32+AL34<=0,"",AL32+AL34)
B38: Observaciones

Sheet Diciembre
B1: CONTROL DE ACTIVIDADES DE CONSULTORÍA | H1: Mes | L1: Año | P1: 13wmqpA-whSNlF58ROWV2OVGTZe15WSD2ofXuk8FfiXE
H2: 12 | L2: =YEAR(P2) -> 2026 | N2: Fecha: | P2: =TODAY() -> 46090
B3: Consultor:
B4: Cargo: | H4: *Período: | K4: =VLOOKUP(H2,Data_Fecha,2,FALSE) -> 46357 | N4: Hasta: | P4: =EOMONTH(K4,0) -> 46387
B5: C.I.#: | F5: Feriado
B6: Gerencia: | D6: {=IF(ISERROR(INDIRECT("Recursos!d"&MATCH($D$3,Recursos!A:A,0))),"",(INDIRECT("Recursos!d"&MATCH($D$3,Recursos!A:A,0))))} | F6: Bancario
B7: Supervisor: | D7: {=INDIRECT("Recursos!f"&MATCH($D$3,Recursos!A:A,0))} -> #N/A
G9: 1 | H9: =+G9+1 -> 2 | I9: =+H9+1 -> 3 | J9: =+I9+1 -> 4 | K9: =+J9+1 -> 5 | L9: =+K9+1 -> 6 | M9: =+L9+1 -> 7 | N9: =+M9+1 -> 8 | O9: =+N9+1 -> 9 | ... AH9: =+AG9+1 -> 28 | AI9: =IF(H2<>"02",+AH9+1,"X") -> 29 | AJ9: =IF(H2<>"02",+AI9+1,"X") -> 30 | AK9: =IF(I2<>"02",+AJ9+1,"X") -> 31
B10: N° | C10: PROYECTO | D10: CLIENTE | E10: SUPERVISOR | F10: ACTIVIDAD | G10: =MID("LMMJVSDL",WEEKDAY($K$4+G$9-2,1),1) -> M | H10: =MID("LMMJVSDL",WEEKDAY($K$4+H$9-2,1),1) -> M | I10: =MID("LMMJVSDL",WEEKDAY($K$4+I$9-2,1),1) -> J | J10: =MID("LMMJVSDL",WEEKDAY($K$4+J$9-2,1),1) -> V | K10: =MID("LMMJVSDL",WEEKDAY($K$4+K$9-2,1),1) -> S | L10: =MID("LMMJVSDL",WEEKDAY($K$4+L$9-2,1),1) -> D | M10: =MID("LMMJVSDL",WEEKDAY($K$4+M$9-2,1),1) -> L | N10: =MID("LMMJVSDL",WEEKDAY($K$4+N$9-2,1),1) -> M | ... AH10: =MID("LMMJVSDL",WEEKDAY($K$4+AH$9-2,1),1) -> L | AI10: =IF(AI11=29,MID("LMMJVSDL",WEEKDAY($K$4+AI$9-2,1),1),"X") -> M | AJ10: =IF(AJ11=30,MID("LMMJVSDL",WEEKDAY($K$4+AJ$9-2,1),1),"X") -> M | AK10: =IF(AK11=31,MID("LMMJVSDL",WEEKDAY($K$4+AK$9-2,1),1),"X") -> J | AL10: TOTAL HORAS
G11: 44470 | H11: =G11+1 -> 44471 | I11: =H11+1 -> 44472 | J11: =I11+1 -> 44473 | K11: =J11+1 -> 44474 | L11: =K11+1 -> 44475 | M11: =L11+1 -> 44476 | N11: =M11+1 -> 44477 | O11: =N11+1 -> 44478 | ... AH11: =AG11+1 -> 44497 | AI11: =AI9 -> 29 | AJ11: =AJ9 -> 30 | AK11: =AK9 -> 31
B12: 1 | AL12: =SUM(G12:AK12) -> 0
B13: =B12+1 -> 2 | AL13: =SUM(G13:AK13) -> 0
B14: =B13+1 -> 3 | AL14: =SUM(G14:AK14) -> 0
B15: =B14+1 -> 4 | AL15: =SUM(G15:AK15) -> 0
B16: =B15+1 -> 5 | AL16: =SUM(G16:AK16) -> 0
B17: =B16+1 -> 6 | AL17: =SUM(G17:AK17) -> 0
B18: =B17+1 -> 7 | AL18: =SUM(G18:AK18) -> 0
B19: =B18+1 -> 8 | AL19: =SUM(G19:AK19) -> 0
B20: =B19+1 -> 9 | AL20: =SUM(G20:AK20) -> 0
B21: =B20+1 -> 10 | AL21: =SUM(G21:AK21) -> 0
B22: =B21+1 -> 11 | AL22: =SUM(G22:AK22) -> 0
B23: =B22+1 -> 12 | AL23: =SUM(G23:AK23) -> 0
B24: =B23+1 -> 13 | AL24: =SUM(G24:AK24) -> 0
... B29: =B28+1 -> 18 | AL29: =SUM(G29:AK29) -> 0
B30: =B29+1 -> 19
B31: =B30+1 -> 20 | AL31: =SUM(G31:AK31) -> 0
C32: =IF(MIN(G32:X32)<8,"EL TOTAL DE HORAS DIARIAS DEBE SER MÍNIMO 8 --->","CORRECTO") -> EL TOTAL DE HORAS DIARIAS DEBE SER MÍNIMO 8 ---> | G32: =SUM(G12:G31) -> 0 | H32: =SUM(H12:H31) -> 0 | I32: =SUM(I12:I31) -> 0 | J32: =SUM(J12:J31) -> 0 | K32: =SUM(K12:K31) -> 0 | L32: =SUM(L12:L31) -> 0 | M32: =SUM(M12:M31) -> 0 | N32: =SUM(N12:N31) -> 0 | ... AL32: =SUM(AL12:AL31) -> 0
F34: Horas Extras (Solo personal autorizado) --- >
F36: TOTAL MES Horas --- > | G36: =IF(G32+G34<=0,"",G32+G34) | H36: =IF(H32+H34<=0,"",H32+H34) | I36: =IF(I32+I34<=0,"",I32+I34) | J36: =IF(J32+J34<=0,"",J32+J34) | K36: =IF(K32+K34<=0,"",K32+K34) | L36: =IF(L32+L34<=0,"",L32+L34) | M36: =IF(M32+M34<=0,"",M32+M34) | N36: =IF(N32+N34<=0,"",N32+N34) | ... AL36: =IF(AL32+AL34<=0,"",AL32+AL34)
B38: Observaciones

Sheet Historial
A1: Nombre y Apellido | B1: Cargo | C1: Documento | D1: Gerencia | E1: Correo | F1: Supervidor
A2: Alex Hernandez Landa | B2: Analista Junior | C2: 20131086 | D2: Operaciones | E2: ahernandez@soaint.com | F2: Luisa Cartaya
A3: Alirio Jose Materano | B3: Consultor Senior | C3: 11590628 | D3: Operaciones | E3: amaterano@soaint.com | F3: Luisa Cartaya
A4: Carbelis Torres Rodriguez | B4: Analista Junior | C4: 25482106 | D4: Operaciones | E4: ctorres@soaint.com | F4: Luisa Cartaya
A5: Christian Maza | B5: Desarrollador | C5: 25846726 | D5: Operaciones | E5: cmaza@soaint.com | F5: Luisa Cartaya
A6: Erika Mata | B6: Desarrollador | C6: 20827059 | D6: Operaciones | E6: emata@soaint.com | F6: Luisa Cartaya
A7: Geomar Milagros Salas | B7: Consultor Junior | C7: 20912350 | D7: Operaciones | E7: gsalas@soaint.com | F7: Luisa Cartaya
A8: Jose Luis Guerra | B8: Analista Senior | C8: 11635322 | D8: Operaciones | E8: jlguerra@soaint.com | F8: Luisa Cartaya
A9: Keiner Ely Negrin Suarez | B9: Consultor junior | C9: 21344016 | D9: Operaciones | E9: knegrin@soaint.com | F9: Luisa Cartaya
A10: Luisa Deneysi Cartaya | B10: Gerente de Operaciones | C10: 10380529 | D10: Operaciones | E10: lcartaya@soaint.com | F10: Alexander Tadeus
A11: Marielba Pérez | B11: Desarrollador | C11: 23707758 | D11: Operaciones | E11: mplopez@soaint.com | F11: Luisa Cartaya
A12: Merci Josefina Fernandez | B12: Desarrollador | C12: 20596224 | D12: Operaciones | E12: mjfernandez@soaint.com | F12: Luisa Cartaya
A13: Oscar Marquez Rodriguez | B13: Consultor de Procesos | C13: 6867929 | D13: Operaciones | E13: omarquez@soaint.com | F13: Luisa Cartaya
... A20: Roberto Briceño | B20: Analista | C20: 26036871 | D20: Operaciones | E20: rbriceno@soaint.com | F20: Luisa Cartaya
